[
  {
    "timestamp": "2025-08-02T07:40:43.536369",
    "avg_processing_time": 9.647708821296693,
    "successful_queries": 50,
    "failed_queries": 0,
    "avg_quality_score": 4.2993550968894585,
    "avg_confidence_score": 0.9768197202432416,
    "memory_usage_mb": 20071.171875,
    "cpu_usage_percent": 2.9,
    "active_sessions": 0
  },
  {
    "timestamp": "2025-08-02T07:41:14.544804",
    "avg_processing_time": 9.647708821296693,
    "successful_queries": 50,
    "failed_queries": 0,
    "avg_quality_score": 4.2993550968894585,
    "avg_confidence_score": 0.9768197202432416,
    "memory_usage_mb": 20145.73046875,
    "cpu_usage_percent": 2.5,
    "active_sessions": 0
  },
  {
    "timestamp": "2025-08-02T07:41:45.555577",
    "avg_processing_time": 9.647708821296693,
    "successful_queries": 50,
    "failed_queries": 0,
    "avg_quality_score": 4.2993550968894585,
    "avg_confidence_score": 0.9768197202432416,
    "memory_usage_mb": 20098.31640625,
    "cpu_usage_percent": 2.0,
    "active_sessions": 0
  },
  {
    "timestamp": "2025-08-02T07:42:16.566147",
    "avg_processing_time": 9.647708821296693,
    "successful_queries": 50,
    "failed_queries": 0,
    "avg_quality_score": 4.2993550968894585,
    "avg_confidence_score": 0.9768197202432416,
    "memory_usage_mb": 20147.51953125,
    "cpu_usage_percent": 1.4,
    "active_sessions": 0
  },
  {
    "timestamp": "2025-08-02T07:42:47.577863",
    "avg_processing_time": 9.647708821296693,
    "successful_queries": 50,
    "failed_queries": 0,
    "avg_quality_score": 4.2993550968894585,
    "avg_confidence_score": 0.9768197202432416,
    "memory_usage_mb": 20127.015625,
    "cpu_usage_percent": 0.9,
    "active_sessions": 0
  },
  {
    "timestamp": "2025-08-02T07:43:18.587893",
    "avg_processing_time": 9.647708821296693,
    "successful_queries": 50,
    "failed_queries": 0,
    "avg_quality_score": 4.2993550968894585,
    "avg_confidence_score": 0.9768197202432416,
    "memory_usage_mb": 20113.75,
    "cpu_usage_percent": 4.6,
    "active_sessions": 0
  },
  {
    "timestamp": "2025-08-02T07:43:49.598119",
    "avg_processing_time": 9.647708821296693,
    "successful_queries": 50,
    "failed_queries": 0,
    "avg_quality_score": 4.2993550968894585,
    "avg_confidence_score": 0.9768197202432416,
    "memory_usage_mb": 20072.72265625,
    "cpu_usage_percent": 0.0,
    "active_sessions": 0
  },
  {
    "timestamp": "2025-08-02T07:44:20.608397",
    "avg_processing_time": 9.647708821296693,
    "successful_queries": 50,
    "failed_queries": 0,
    "avg_quality_score": 4.2993550968894585,
    "avg_confidence_score": 0.9768197202432416,
    "memory_usage_mb": 20129.5078125,
    "cpu_usage_percent": 2.9,
    "active_sessions": 0
  },
  {
    "timestamp": "2025-08-02T07:44:51.619013",
    "avg_processing_time": 9.647708821296693,
    "successful_queries": 50,
    "failed_queries": 0,
    "avg_quality_score": 4.2993550968894585,
    "avg_confidence_score": 0.9768197202432416,
    "memory_usage_mb": 20060.10546875,
    "cpu_usage_percent": 3.2,
    "active_sessions": 0
  },
  {
    "timestamp": "2025-08-02T07:45:22.631903",
    "avg_processing_time": 9.647708821296693,
    "successful_queries": 50,
    "failed_queries": 0,
    "avg_quality_score": 4.2993550968894585,
    "avg_confidence_score": 0.9768197202432416,
    "memory_usage_mb": 20093.234375,
    "cpu_usage_percent": 2.9,
    "active_sessions": 0
  },
  {
    "timestamp": "2025-08-02T07:45:53.642442",
    "avg_processing_time": 9.647708821296693,
    "successful_queries": 50,
    "failed_queries": 0,
    "avg_quality_score": 4.2993550968894585,
    "avg_confidence_score": 0.9768197202432416,
    "memory_usage_mb": 20047.16015625,
    "cpu_usage_percent": 1.3,
    "active_sessions": 0
  },
  {
    "timestamp": "2025-08-02T07:46:24.651772",
    "avg_processing_time": 9.647708821296693,
    "successful_queries": 50,
    "failed_queries": 0,
    "avg_quality_score": 4.2993550968894585,
    "avg_confidence_score": 0.9768197202432416,
    "memory_usage_mb": 20106.0546875,
    "cpu_usage_percent": 1.2,
    "active_sessions": 0
  },
  {
    "timestamp": "2025-08-02T07:46:55.662222",
    "avg_processing_time": 9.647708821296693,
    "successful_queries": 50,
    "failed_queries": 0,
    "avg_quality_score": 4.2993550968894585,
    "avg_confidence_score": 0.9768197202432416,
    "memory_usage_mb": 20102.77734375,
    "cpu_usage_percent": 11.4,
    "active_sessions": 0
  },
  {
    "timestamp": "2025-08-02T07:47:26.676824",
    "avg_processing_time": 9.647708821296693,
    "successful_queries": 50,
    "failed_queries": 0,
    "avg_quality_score": 4.2993550968894585,
    "avg_confidence_score": 0.9768197202432416,
    "memory_usage_mb": 20084.21484375,
    "cpu_usage_percent": 3.1,
    "active_sessions": 0
  },
  {
    "timestamp": "2025-08-02T07:47:57.689820",
    "avg_processing_time": 9.647708821296693,
    "successful_queries": 50,
    "failed_queries": 0,
    "avg_quality_score": 4.2993550968894585,
    "avg_confidence_score": 0.9768197202432416,
    "memory_usage_mb": 20070.7421875,
    "cpu_usage_percent": 8.0,
    "active_sessions": 0
  },
  {
    "timestamp": "2025-08-02T07:48:28.700782",
    "avg_processing_time": 9.647708821296693,
    "successful_queries": 50,
    "failed_queries": 0,
    "avg_quality_score": 4.2993550968894585,
    "avg_confidence_score": 0.9768197202432416,
    "memory_usage_mb": 20084.21875,
    "cpu_usage_percent": 1.2,
    "active_sessions": 0
  },
  {
    "timestamp": "2025-08-02T07:48:59.710694",
    "avg_processing_time": 9.647708821296693,
    "successful_queries": 50,
    "failed_queries": 0,
    "avg_quality_score": 4.2993550968894585,
    "avg_confidence_score": 0.9768197202432416,
    "memory_usage_mb": 20090.4296875,
    "cpu_usage_percent": 14.2,
    "active_sessions": 0
  },
  {
    "timestamp": "2025-08-02T07:49:30.733391",
    "avg_processing_time": 9.647708821296693,
    "successful_queries": 50,
    "failed_queries": 0,
    "avg_quality_score": 4.2993550968894585,
    "avg_confidence_score": 0.9768197202432416,
    "memory_usage_mb": 20077.38671875,
    "cpu_usage_percent": 3.1,
    "active_sessions": 0
  },
  {
    "timestamp": "2025-08-02T07:50:01.743843",
    "avg_processing_time": 9.647708821296693,
    "successful_queries": 50,
    "failed_queries": 0,
    "avg_quality_score": 4.2993550968894585,
    "avg_confidence_score": 0.9768197202432416,
    "memory_usage_mb": 20201.34375,
    "cpu_usage_percent": 1.7,
    "active_sessions": 0
  },
  {
    "timestamp": "2025-08-02T07:50:32.758612",
    "avg_processing_time": 9.647708821296693,
    "successful_queries": 50,
    "failed_queries": 0,
    "avg_quality_score": 4.2993550968894585,
    "avg_confidence_score": 0.9768197202432416,
    "memory_usage_mb": 20062.98046875,
    "cpu_usage_percent": 8.7,
    "active_sessions": 0
  },
  {
    "timestamp": "2025-08-02T07:51:03.778291",
    "avg_processing_time": 9.647708821296693,
    "successful_queries": 50,
    "failed_queries": 0,
    "avg_quality_score": 4.2993550968894585,
    "avg_confidence_score": 0.9768197202432416,
    "memory_usage_mb": 20120.25390625,
    "cpu_usage_percent": 2.4,
    "active_sessions": 0
  },
  {
    "timestamp": "2025-08-02T07:51:34.789201",
    "avg_processing_time": 9.647708821296693,
    "successful_queries": 50,
    "failed_queries": 0,
    "avg_quality_score": 4.2993550968894585,
    "avg_confidence_score": 0.9768197202432416,
    "memory_usage_mb": 20105.14453125,
    "cpu_usage_percent": 10.4,
    "active_sessions": 0
  },
  {
    "timestamp": "2025-08-02T07:52:05.803467",
    "avg_processing_time": 9.647708821296693,
    "successful_queries": 50,
    "failed_queries": 0,
    "avg_quality_score": 4.2993550968894585,
    "avg_confidence_score": 0.9768197202432416,
    "memory_usage_mb": 20015.6484375,
    "cpu_usage_percent": 1.7,
    "active_sessions": 0
  },
  {
    "timestamp": "2025-08-02T07:52:36.814380",
    "avg_processing_time": 9.647708821296693,
    "successful_queries": 50,
    "failed_queries": 0,
    "avg_quality_score": 4.2993550968894585,
    "avg_confidence_score": 0.9768197202432416,
    "memory_usage_mb": 20004.23046875,
    "cpu_usage_percent": 1.6,
    "active_sessions": 0
  },
  {
    "timestamp": "2025-08-02T07:53:07.824449",
    "avg_processing_time": 9.647708821296693,
    "successful_queries": 50,
    "failed_queries": 0,
    "avg_quality_score": 4.2993550968894585,
    "avg_confidence_score": 0.9768197202432416,
    "memory_usage_mb": 20029.23828125,
    "cpu_usage_percent": 2.2,
    "active_sessions": 0
  },
  {
    "timestamp": "2025-08-02T07:53:38.835370",
    "avg_processing_time": 9.647708821296693,
    "successful_queries": 50,
    "failed_queries": 0,
    "avg_quality_score": 4.2993550968894585,
    "avg_confidence_score": 0.9768197202432416,
    "memory_usage_mb": 19945.05859375,
    "cpu_usage_percent": 1.4,
    "active_sessions": 0
  },
  {
    "timestamp": "2025-08-02T07:54:09.846501",
    "avg_processing_time": 9.647708821296693,
    "successful_queries": 50,
    "failed_queries": 0,
    "avg_quality_score": 4.2993550968894585,
    "avg_confidence_score": 0.9768197202432416,
    "memory_usage_mb": 20122.63671875,
    "cpu_usage_percent": 3.7,
    "active_sessions": 0
  },
  {
    "timestamp": "2025-08-02T07:54:40.857141",
    "avg_processing_time": 9.647708821296693,
    "successful_queries": 50,
    "failed_queries": 0,
    "avg_quality_score": 4.2993550968894585,
    "avg_confidence_score": 0.9768197202432416,
    "memory_usage_mb": 20022.83984375,
    "cpu_usage_percent": 0.8,
    "active_sessions": 0
  },
  {
    "timestamp": "2025-08-02T07:55:11.867982",
    "avg_processing_time": 9.647708821296693,
    "successful_queries": 50,
    "failed_queries": 0,
    "avg_quality_score": 4.2993550968894585,
    "avg_confidence_score": 0.9768197202432416,
    "memory_usage_mb": 21170.90625,
    "cpu_usage_percent": 7.1,
    "active_sessions": 0
  },
  {
    "timestamp": "2025-08-02T07:55:42.884473",
    "avg_processing_time": 9.647708821296693,
    "successful_queries": 50,
    "failed_queries": 0,
    "avg_quality_score": 4.2993550968894585,
    "avg_confidence_score": 0.9768197202432416,
    "memory_usage_mb": 20716.0078125,
    "cpu_usage_percent": 8.2,
    "active_sessions": 0
  },
  {
    "timestamp": "2025-08-02T07:56:13.895613",
    "avg_processing_time": 9.647708821296693,
    "successful_queries": 50,
    "failed_queries": 0,
    "avg_quality_score": 4.2993550968894585,
    "avg_confidence_score": 0.9768197202432416,
    "memory_usage_mb": 20903.0078125,
    "cpu_usage_percent": 2.6,
    "active_sessions": 0
  },
  {
    "timestamp": "2025-08-02T07:56:44.906037",
    "avg_processing_time": 9.647708821296693,
    "successful_queries": 50,
    "failed_queries": 0,
    "avg_quality_score": 4.2993550968894585,
    "avg_confidence_score": 0.9768197202432416,
    "memory_usage_mb": 20718.8671875,
    "cpu_usage_percent": 7.8,
    "active_sessions": 0
  },
  {
    "timestamp": "2025-08-02T07:57:15.916446",
    "avg_processing_time": 9.647708821296693,
    "successful_queries": 50,
    "failed_queries": 0,
    "avg_quality_score": 4.2993550968894585,
    "avg_confidence_score": 0.9768197202432416,
    "memory_usage_mb": 20746.37890625,
    "cpu_usage_percent": 1.9,
    "active_sessions": 0
  },
  {
    "timestamp": "2025-08-02T07:57:46.926934",
    "avg_processing_time": 9.647708821296693,
    "successful_queries": 50,
    "failed_queries": 0,
    "avg_quality_score": 4.2993550968894585,
    "avg_confidence_score": 0.9768197202432416,
    "memory_usage_mb": 20641.859375,
    "cpu_usage_percent": 2.7,
    "active_sessions": 0
  },
  {
    "timestamp": "2025-08-02T07:58:17.937710",
    "avg_processing_time": 9.647708821296693,
    "successful_queries": 50,
    "failed_queries": 0,
    "avg_quality_score": 4.2993550968894585,
    "avg_confidence_score": 0.9768197202432416,
    "memory_usage_mb": 20757.1953125,
    "cpu_usage_percent": 2.6,
    "active_sessions": 0
  },
  {
    "timestamp": "2025-08-02T07:58:48.948466",
    "avg_processing_time": 9.647708821296693,
    "successful_queries": 50,
    "failed_queries": 0,
    "avg_quality_score": 4.2993550968894585,
    "avg_confidence_score": 0.9768197202432416,
    "memory_usage_mb": 20797.19921875,
    "cpu_usage_percent": 2.1,
    "active_sessions": 0
  },
  {
    "timestamp": "2025-08-02T07:59:19.959109",
    "avg_processing_time": 9.647708821296693,
    "successful_queries": 50,
    "failed_queries": 0,
    "avg_quality_score": 4.2993550968894585,
    "avg_confidence_score": 0.9768197202432416,
    "memory_usage_mb": 20656.68359375,
    "cpu_usage_percent": 7.8,
    "active_sessions": 0
  },
  {
    "timestamp": "2025-08-02T07:59:50.969301",
    "avg_processing_time": 9.647708821296693,
    "successful_queries": 50,
    "failed_queries": 0,
    "avg_quality_score": 4.2993550968894585,
    "avg_confidence_score": 0.9768197202432416,
    "memory_usage_mb": 20726.578125,
    "cpu_usage_percent": 1.4,
    "active_sessions": 0
  },
  {
    "timestamp": "2025-08-02T08:00:21.979352",
    "avg_processing_time": 9.647708821296693,
    "successful_queries": 50,
    "failed_queries": 0,
    "avg_quality_score": 4.2993550968894585,
    "avg_confidence_score": 0.9768197202432416,
    "memory_usage_mb": 21017.01953125,
    "cpu_usage_percent": 4.2,
    "active_sessions": 0
  },
  {
    "timestamp": "2025-08-02T08:00:52.990093",
    "avg_processing_time": 9.647708821296693,
    "successful_queries": 50,
    "failed_queries": 0,
    "avg_quality_score": 4.2993550968894585,
    "avg_confidence_score": 0.9768197202432416,
    "memory_usage_mb": 21263.77734375,
    "cpu_usage_percent": 6.1,
    "active_sessions": 0
  },
  {
    "timestamp": "2025-08-02T08:01:24.001379",
    "avg_processing_time": 9.647708821296693,
    "successful_queries": 50,
    "failed_queries": 0,
    "avg_quality_score": 4.2993550968894585,
    "avg_confidence_score": 0.9768197202432416,
    "memory_usage_mb": 21287.95703125,
    "cpu_usage_percent": 5.6,
    "active_sessions": 0
  },
  {
    "timestamp": "2025-08-02T08:01:55.026506",
    "avg_processing_time": 9.647708821296693,
    "successful_queries": 50,
    "failed_queries": 0,
    "avg_quality_score": 4.2993550968894585,
    "avg_confidence_score": 0.9768197202432416,
    "memory_usage_mb": 20891.50390625,
    "cpu_usage_percent": 25.4,
    "active_sessions": 0
  },
  {
    "timestamp": "2025-08-02T08:02:26.045459",
    "avg_processing_time": 9.647708821296693,
    "successful_queries": 50,
    "failed_queries": 0,
    "avg_quality_score": 4.2993550968894585,
    "avg_confidence_score": 0.9768197202432416,
    "memory_usage_mb": 20873.9921875,
    "cpu_usage_percent": 8.7,
    "active_sessions": 0
  },
  {
    "timestamp": "2025-08-02T08:02:57.057971",
    "avg_processing_time": 9.647708821296693,
    "successful_queries": 50,
    "failed_queries": 0,
    "avg_quality_score": 4.2993550968894585,
    "avg_confidence_score": 0.9768197202432416,
    "memory_usage_mb": 20443.2109375,
    "cpu_usage_percent": 2.6,
    "active_sessions": 0
  },
  {
    "timestamp": "2025-08-02T08:03:28.068013",
    "avg_processing_time": 9.647708821296693,
    "successful_queries": 50,
    "failed_queries": 0,
    "avg_quality_score": 4.2993550968894585,
    "avg_confidence_score": 0.9768197202432416,
    "memory_usage_mb": 20464.59375,
    "cpu_usage_percent": 2.5,
    "active_sessions": 0
  },
  {
    "timestamp": "2025-08-02T08:03:59.078683",
    "avg_processing_time": 9.647708821296693,
    "successful_queries": 50,
    "failed_queries": 0,
    "avg_quality_score": 4.2993550968894585,
    "avg_confidence_score": 0.9768197202432416,
    "memory_usage_mb": 20223.31640625,
    "cpu_usage_percent": 11.9,
    "active_sessions": 0
  },
  {
    "timestamp": "2025-08-02T08:04:30.092948",
    "avg_processing_time": 9.647708821296693,
    "successful_queries": 50,
    "failed_queries": 0,
    "avg_quality_score": 4.2993550968894585,
    "avg_confidence_score": 0.9768197202432416,
    "memory_usage_mb": 20711.4921875,
    "cpu_usage_percent": 4.8,
    "active_sessions": 0
  },
  {
    "timestamp": "2025-08-02T08:05:01.103687",
    "avg_processing_time": 9.647708821296693,
    "successful_queries": 50,
    "failed_queries": 0,
    "avg_quality_score": 4.2993550968894585,
    "avg_confidence_score": 0.9768197202432416,
    "memory_usage_mb": 20488.21875,
    "cpu_usage_percent": 25.9,
    "active_sessions": 0
  },
  {
    "timestamp": "2025-08-02T08:05:32.114934",
    "avg_processing_time": 9.647708821296693,
    "successful_queries": 50,
    "failed_queries": 0,
    "avg_quality_score": 4.2993550968894585,
    "avg_confidence_score": 0.9768197202432416,
    "memory_usage_mb": 20518.234375,
    "cpu_usage_percent": 5.6,
    "active_sessions": 0
  },
  {
    "timestamp": "2025-08-02T08:06:03.126084",
    "avg_processing_time": 9.647708821296693,
    "successful_queries": 50,
    "failed_queries": 0,
    "avg_quality_score": 4.2993550968894585,
    "avg_confidence_score": 0.9768197202432416,
    "memory_usage_mb": 20333.125,
    "cpu_usage_percent": 3.5,
    "active_sessions": 0
  },
  {
    "timestamp": "2025-08-02T08:06:34.136661",
    "avg_processing_time": 9.647708821296693,
    "successful_queries": 50,
    "failed_queries": 0,
    "avg_quality_score": 4.2993550968894585,
    "avg_confidence_score": 0.9768197202432416,
    "memory_usage_mb": 20277.7734375,
    "cpu_usage_percent": 11.2,
    "active_sessions": 0
  },
  {
    "timestamp": "2025-08-02T08:07:05.147202",
    "avg_processing_time": 9.647708821296693,
    "successful_queries": 50,
    "failed_queries": 0,
    "avg_quality_score": 4.2993550968894585,
    "avg_confidence_score": 0.9768197202432416,
    "memory_usage_mb": 20361.01953125,
    "cpu_usage_percent": 7.5,
    "active_sessions": 0
  },
  {
    "timestamp": "2025-08-02T08:07:36.157760",
    "avg_processing_time": 9.647708821296693,
    "successful_queries": 50,
    "failed_queries": 0,
    "avg_quality_score": 4.2993550968894585,
    "avg_confidence_score": 0.9768197202432416,
    "memory_usage_mb": 20924.64453125,
    "cpu_usage_percent": 1.3,
    "active_sessions": 0
  },
  {
    "timestamp": "2025-08-02T08:08:07.167832",
    "avg_processing_time": 9.647708821296693,
    "successful_queries": 50,
    "failed_queries": 0,
    "avg_quality_score": 4.2993550968894585,
    "avg_confidence_score": 0.9768197202432416,
    "memory_usage_mb": 21285.796875,
    "cpu_usage_percent": 5.2,
    "active_sessions": 0
  },
  {
    "timestamp": "2025-08-02T08:08:38.178363",
    "avg_processing_time": 9.647708821296693,
    "successful_queries": 50,
    "failed_queries": 0,
    "avg_quality_score": 4.2993550968894585,
    "avg_confidence_score": 0.9768197202432416,
    "memory_usage_mb": 22573.296875,
    "cpu_usage_percent": 54.8,
    "active_sessions": 0
  },
  {
    "timestamp": "2025-08-02T08:09:09.194391",
    "avg_processing_time": 9.647708821296693,
    "successful_queries": 50,
    "failed_queries": 0,
    "avg_quality_score": 4.2993550968894585,
    "avg_confidence_score": 0.9768197202432416,
    "memory_usage_mb": 22906.2109375,
    "cpu_usage_percent": 58.0,
    "active_sessions": 0
  },
  {
    "timestamp": "2025-08-02T08:09:40.211317",
    "avg_processing_time": 9.647708821296693,
    "successful_queries": 50,
    "failed_queries": 0,
    "avg_quality_score": 4.2993550968894585,
    "avg_confidence_score": 0.9768197202432416,
    "memory_usage_mb": 22971.09375,
    "cpu_usage_percent": 20.0,
    "active_sessions": 0
  },
  {
    "timestamp": "2025-08-02T08:10:11.245809",
    "avg_processing_time": 9.647708821296693,
    "successful_queries": 50,
    "failed_queries": 0,
    "avg_quality_score": 4.2993550968894585,
    "avg_confidence_score": 0.9768197202432416,
    "memory_usage_mb": 22642.9296875,
    "cpu_usage_percent": 16.8,
    "active_sessions": 0
  },
  {
    "timestamp": "2025-08-02T08:10:42.257626",
    "avg_processing_time": 9.647708821296693,
    "successful_queries": 50,
    "failed_queries": 0,
    "avg_quality_score": 4.2993550968894585,
    "avg_confidence_score": 0.9768197202432416,
    "memory_usage_mb": 22381.8046875,
    "cpu_usage_percent": 47.4,
    "active_sessions": 0
  },
  {
    "timestamp": "2025-08-02T08:11:13.309397",
    "avg_processing_time": 9.647708821296693,
    "successful_queries": 50,
    "failed_queries": 0,
    "avg_quality_score": 4.2993550968894585,
    "avg_confidence_score": 0.9768197202432416,
    "memory_usage_mb": 22354.1171875,
    "cpu_usage_percent": 18.7,
    "active_sessions": 0
  },
  {
    "timestamp": "2025-08-02T08:11:44.321823",
    "avg_processing_time": 9.647708821296693,
    "successful_queries": 50,
    "failed_queries": 0,
    "avg_quality_score": 4.2993550968894585,
    "avg_confidence_score": 0.9768197202432416,
    "memory_usage_mb": 22327.2578125,
    "cpu_usage_percent": 20.2,
    "active_sessions": 0
  },
  {
    "timestamp": "2025-08-02T08:12:15.360057",
    "avg_processing_time": 9.647708821296693,
    "successful_queries": 50,
    "failed_queries": 0,
    "avg_quality_score": 4.2993550968894585,
    "avg_confidence_score": 0.9768197202432416,
    "memory_usage_mb": 22255.9140625,
    "cpu_usage_percent": 100.0,
    "active_sessions": 0
  },
  {
    "timestamp": "2025-08-02T08:12:46.429681",
    "avg_processing_time": 9.647708821296693,
    "successful_queries": 50,
    "failed_queries": 0,
    "avg_quality_score": 4.2993550968894585,
    "avg_confidence_score": 0.9768197202432416,
    "memory_usage_mb": 23533.28125,
    "cpu_usage_percent": 100.0,
    "active_sessions": 0
  },
  {
    "timestamp": "2025-08-02T08:13:17.638605",
    "avg_processing_time": 9.647708821296693,
    "successful_queries": 50,
    "failed_queries": 0,
    "avg_quality_score": 4.2993550968894585,
    "avg_confidence_score": 0.9768197202432416,
    "memory_usage_mb": 23679.1328125,
    "cpu_usage_percent": 34.3,
    "active_sessions": 0
  },
  {
    "timestamp": "2025-08-02T08:13:48.660399",
    "avg_processing_time": 9.647708821296693,
    "successful_queries": 50,
    "failed_queries": 0,
    "avg_quality_score": 4.2993550968894585,
    "avg_confidence_score": 0.9768197202432416,
    "memory_usage_mb": 23663.63671875,
    "cpu_usage_percent": 56.8,
    "active_sessions": 0
  },
  {
    "timestamp": "2025-08-02T08:14:19.703305",
    "avg_processing_time": 9.647708821296693,
    "successful_queries": 50,
    "failed_queries": 0,
    "avg_quality_score": 4.2993550968894585,
    "avg_confidence_score": 0.9768197202432416,
    "memory_usage_mb": 23689.86328125,
    "cpu_usage_percent": 26.4,
    "active_sessions": 0
  },
  {
    "timestamp": "2025-08-02T08:14:50.717557",
    "avg_processing_time": 9.647708821296693,
    "successful_queries": 50,
    "failed_queries": 0,
    "avg_quality_score": 4.2993550968894585,
    "avg_confidence_score": 0.9768197202432416,
    "memory_usage_mb": 23537.91796875,
    "cpu_usage_percent": 26.1,
    "active_sessions": 0
  },
  {
    "timestamp": "2025-08-02T08:15:21.731713",
    "avg_processing_time": 9.647708821296693,
    "successful_queries": 50,
    "failed_queries": 0,
    "avg_quality_score": 4.2993550968894585,
    "avg_confidence_score": 0.9768197202432416,
    "memory_usage_mb": 23591.73828125,
    "cpu_usage_percent": 24.0,
    "active_sessions": 0
  },
  {
    "timestamp": "2025-08-02T08:15:52.766852",
    "avg_processing_time": 10.108961334228516,
    "successful_queries": 50,
    "failed_queries": 0,
    "avg_quality_score": 4.324355096889459,
    "avg_confidence_score": 0.9769140611027998,
    "memory_usage_mb": 24340.04296875,
    "cpu_usage_percent": 34.0,
    "active_sessions": 0
  },
  {
    "timestamp": "2025-08-02T08:16:23.786954",
    "avg_processing_time": 10.108961334228516,
    "successful_queries": 50,
    "failed_queries": 0,
    "avg_quality_score": 4.324355096889459,
    "avg_confidence_score": 0.9769140611027998,
    "memory_usage_mb": 24793.234375,
    "cpu_usage_percent": 100.0,
    "active_sessions": 0
  },
  {
    "timestamp": "2025-08-02T08:16:55.013092",
    "avg_processing_time": 10.108961334228516,
    "successful_queries": 50,
    "failed_queries": 0,
    "avg_quality_score": 4.324355096889459,
    "avg_confidence_score": 0.9769140611027998,
    "memory_usage_mb": 25070.8046875,
    "cpu_usage_percent": 17.5,
    "active_sessions": 0
  },
  {
    "timestamp": "2025-08-02T08:17:42.599979",
    "avg_processing_time": 10.108961334228516,
    "successful_queries": 50,
    "failed_queries": 0,
    "avg_quality_score": 4.324355096889459,
    "avg_confidence_score": 0.9769140611027998,
    "memory_usage_mb": 23413.98828125,
    "cpu_usage_percent": 12.2,
    "active_sessions": 0
  },
  {
    "timestamp": "2025-08-02T08:18:06.245093",
    "avg_processing_time": 10.108961334228516,
    "successful_queries": 50,
    "failed_queries": 0,
    "avg_quality_score": 4.324355096889459,
    "avg_confidence_score": 0.9769140611027998,
    "memory_usage_mb": 23554.7109375,
    "cpu_usage_percent": 11.5,
    "active_sessions": 0
  },
  {
    "timestamp": "2025-08-02T08:18:37.274010",
    "avg_processing_time": 10.108961334228516,
    "successful_queries": 50,
    "failed_queries": 0,
    "avg_quality_score": 4.324355096889459,
    "avg_confidence_score": 0.9769140611027998,
    "memory_usage_mb": 24009.94921875,
    "cpu_usage_percent": 36.0,
    "active_sessions": 0
  },
  {
    "timestamp": "2025-08-02T08:19:08.286893",
    "avg_processing_time": 10.108961334228516,
    "successful_queries": 50,
    "failed_queries": 0,
    "avg_quality_score": 4.324355096889459,
    "avg_confidence_score": 0.9769140611027998,
    "memory_usage_mb": 23841.453125,
    "cpu_usage_percent": 44.2,
    "active_sessions": 0
  },
  {
    "timestamp": "2025-08-02T08:19:39.312131",
    "avg_processing_time": 10.108961334228516,
    "successful_queries": 50,
    "failed_queries": 0,
    "avg_quality_score": 4.324355096889459,
    "avg_confidence_score": 0.9769140611027998,
    "memory_usage_mb": 22957.4609375,
    "cpu_usage_percent": 100.0,
    "active_sessions": 0
  },
  {
    "timestamp": "2025-08-02T08:20:10.427456",
    "avg_processing_time": 10.108961334228516,
    "successful_queries": 50,
    "failed_queries": 0,
    "avg_quality_score": 4.324355096889459,
    "avg_confidence_score": 0.9769140611027998,
    "memory_usage_mb": 23288.51171875,
    "cpu_usage_percent": 7.4,
    "active_sessions": 0
  },
  {
    "timestamp": "2025-08-02T08:20:41.438891",
    "avg_processing_time": 10.108961334228516,
    "successful_queries": 50,
    "failed_queries": 0,
    "avg_quality_score": 4.324355096889459,
    "avg_confidence_score": 0.9769140611027998,
    "memory_usage_mb": 22919.84375,
    "cpu_usage_percent": 4.7,
    "active_sessions": 0
  },
  {
    "timestamp": "2025-08-02T08:21:12.450775",
    "avg_processing_time": 10.108961334228516,
    "successful_queries": 50,
    "failed_queries": 0,
    "avg_quality_score": 4.324355096889459,
    "avg_confidence_score": 0.9769140611027998,
    "memory_usage_mb": 21956.46875,
    "cpu_usage_percent": 4.9,
    "active_sessions": 0
  },
  {
    "timestamp": "2025-08-02T08:21:43.461984",
    "avg_processing_time": 10.108961334228516,
    "successful_queries": 50,
    "failed_queries": 0,
    "avg_quality_score": 4.324355096889459,
    "avg_confidence_score": 0.9769140611027998,
    "memory_usage_mb": 22077.79296875,
    "cpu_usage_percent": 37.3,
    "active_sessions": 0
  },
  {
    "timestamp": "2025-08-02T08:22:14.476490",
    "avg_processing_time": 10.108961334228516,
    "successful_queries": 50,
    "failed_queries": 0,
    "avg_quality_score": 4.324355096889459,
    "avg_confidence_score": 0.9769140611027998,
    "memory_usage_mb": 21524.30859375,
    "cpu_usage_percent": 40.1,
    "active_sessions": 0
  },
  {
    "timestamp": "2025-08-02T08:22:45.492116",
    "avg_processing_time": 10.108961334228516,
    "successful_queries": 50,
    "failed_queries": 0,
    "avg_quality_score": 4.324355096889459,
    "avg_confidence_score": 0.9769140611027998,
    "memory_usage_mb": 21689.73046875,
    "cpu_usage_percent": 51.0,
    "active_sessions": 0
  },
  {
    "timestamp": "2025-08-02T08:23:16.509431",
    "avg_processing_time": 10.108961334228516,
    "successful_queries": 50,
    "failed_queries": 0,
    "avg_quality_score": 4.324355096889459,
    "avg_confidence_score": 0.9769140611027998,
    "memory_usage_mb": 21619.3515625,
    "cpu_usage_percent": 52.7,
    "active_sessions": 0
  },
  {
    "timestamp": "2025-08-02T08:23:47.537295",
    "avg_processing_time": 10.108961334228516,
    "successful_queries": 50,
    "failed_queries": 0,
    "avg_quality_score": 4.324355096889459,
    "avg_confidence_score": 0.9769140611027998,
    "memory_usage_mb": 21792.40625,
    "cpu_usage_percent": 36.9,
    "active_sessions": 0
  },
  {
    "timestamp": "2025-08-02T08:24:18.557311",
    "avg_processing_time": 10.108961334228516,
    "successful_queries": 50,
    "failed_queries": 0,
    "avg_quality_score": 4.324355096889459,
    "avg_confidence_score": 0.9769140611027998,
    "memory_usage_mb": 21864.1171875,
    "cpu_usage_percent": 48.0,
    "active_sessions": 0
  },
  {
    "timestamp": "2025-08-02T08:24:49.595903",
    "avg_processing_time": 10.108961334228516,
    "successful_queries": 50,
    "failed_queries": 0,
    "avg_quality_score": 4.324355096889459,
    "avg_confidence_score": 0.9769140611027998,
    "memory_usage_mb": 21817.453125,
    "cpu_usage_percent": 49.7,
    "active_sessions": 0
  },
  {
    "timestamp": "2025-08-02T08:25:20.613008",
    "avg_processing_time": 10.108961334228516,
    "successful_queries": 50,
    "failed_queries": 0,
    "avg_quality_score": 4.324355096889459,
    "avg_confidence_score": 0.9769140611027998,
    "memory_usage_mb": 22173.921875,
    "cpu_usage_percent": 43.2,
    "active_sessions": 0
  },
  {
    "timestamp": "2025-08-02T08:25:51.626964",
    "avg_processing_time": 10.108961334228516,
    "successful_queries": 50,
    "failed_queries": 0,
    "avg_quality_score": 4.324355096889459,
    "avg_confidence_score": 0.9769140611027998,
    "memory_usage_mb": 22544.34375,
    "cpu_usage_percent": 50.4,
    "active_sessions": 0
  },
  {
    "timestamp": "2025-08-02T08:26:22.641902",
    "avg_processing_time": 10.108961334228516,
    "successful_queries": 50,
    "failed_queries": 0,
    "avg_quality_score": 4.324355096889459,
    "avg_confidence_score": 0.9769140611027998,
    "memory_usage_mb": 21835.00390625,
    "cpu_usage_percent": 41.8,
    "active_sessions": 0
  },
  {
    "timestamp": "2025-08-02T08:26:53.674018",
    "avg_processing_time": 10.108961334228516,
    "successful_queries": 50,
    "failed_queries": 0,
    "avg_quality_score": 4.324355096889459,
    "avg_confidence_score": 0.9769140611027998,
    "memory_usage_mb": 22023.41015625,
    "cpu_usage_percent": 44.9,
    "active_sessions": 0
  },
  {
    "timestamp": "2025-08-02T08:27:24.689498",
    "avg_processing_time": 10.108961334228516,
    "successful_queries": 50,
    "failed_queries": 0,
    "avg_quality_score": 4.324355096889459,
    "avg_confidence_score": 0.9769140611027998,
    "memory_usage_mb": 21353.11328125,
    "cpu_usage_percent": 45.5,
    "active_sessions": 0
  },
  {
    "timestamp": "2025-08-02T08:27:55.704715",
    "avg_processing_time": 10.108961334228516,
    "successful_queries": 50,
    "failed_queries": 0,
    "avg_quality_score": 4.324355096889459,
    "avg_confidence_score": 0.9769140611027998,
    "memory_usage_mb": 21558.43359375,
    "cpu_usage_percent": 38.0,
    "active_sessions": 0
  },
  {
    "timestamp": "2025-08-02T08:28:26.720730",
    "avg_processing_time": 10.108961334228516,
    "successful_queries": 50,
    "failed_queries": 0,
    "avg_quality_score": 4.324355096889459,
    "avg_confidence_score": 0.9769140611027998,
    "memory_usage_mb": 21690.41015625,
    "cpu_usage_percent": 31.0,
    "active_sessions": 0
  },
  {
    "timestamp": "2025-08-02T08:28:57.735972",
    "avg_processing_time": 10.108961334228516,
    "successful_queries": 50,
    "failed_queries": 0,
    "avg_quality_score": 4.324355096889459,
    "avg_confidence_score": 0.9769140611027998,
    "memory_usage_mb": 21585.8671875,
    "cpu_usage_percent": 48.0,
    "active_sessions": 0
  },
  {
    "timestamp": "2025-08-02T08:29:28.750353",
    "avg_processing_time": 10.108961334228516,
    "successful_queries": 50,
    "failed_queries": 0,
    "avg_quality_score": 4.324355096889459,
    "avg_confidence_score": 0.9769140611027998,
    "memory_usage_mb": 21998.37109375,
    "cpu_usage_percent": 41.0,
    "active_sessions": 0
  },
  {
    "timestamp": "2025-08-02T08:30:14.750068",
    "avg_processing_time": 10.108961334228516,
    "successful_queries": 50,
    "failed_queries": 0,
    "avg_quality_score": 4.324355096889459,
    "avg_confidence_score": 0.9769140611027998,
    "memory_usage_mb": 21628.10546875,
    "cpu_usage_percent": 51.4,
    "active_sessions": 0
  },
  {
    "timestamp": "2025-08-02T08:30:45.813524",
    "avg_processing_time": 10.108961334228516,
    "successful_queries": 50,
    "failed_queries": 0,
    "avg_quality_score": 4.324355096889459,
    "avg_confidence_score": 0.9769140611027998,
    "memory_usage_mb": 21678.5078125,
    "cpu_usage_percent": 100.0,
    "active_sessions": 0
  },
  {
    "timestamp": "2025-08-02T08:31:18.100441",
    "avg_processing_time": 10.108961334228516,
    "successful_queries": 50,
    "failed_queries": 0,
    "avg_quality_score": 4.324355096889459,
    "avg_confidence_score": 0.9769140611027998,
    "memory_usage_mb": 21238.1796875,
    "cpu_usage_percent": 51.7,
    "active_sessions": 0
  },
  {
    "timestamp": "2025-08-02T08:31:49.121027",
    "avg_processing_time": 10.108961334228516,
    "successful_queries": 50,
    "failed_queries": 0,
    "avg_quality_score": 4.324355096889459,
    "avg_confidence_score": 0.9769140611027998,
    "memory_usage_mb": 21531.6796875,
    "cpu_usage_percent": 31.0,
    "active_sessions": 0
  },
  {
    "timestamp": "2025-08-02T08:32:20.136041",
    "avg_processing_time": 10.108961334228516,
    "successful_queries": 50,
    "failed_queries": 0,
    "avg_quality_score": 4.324355096889459,
    "avg_confidence_score": 0.9769140611027998,
    "memory_usage_mb": 21255.1953125,
    "cpu_usage_percent": 18.9,
    "active_sessions": 0
  }
]